{
    "fdsa": {
        "stu0": "Absent",
        "stu1": "Present",
        "stu2": "Present",
        "stu3": "Absent",
        "stu4": "Absent",
        "stu5": "Absent",
        "stu6": "Absent",
        "stu7": "Absent",
        "stu8": "Absent",
        "stu9": "Absent",
        "stu10": "Absent",
        "stu11": "Absent",
        "stu12": "Absent",
        "stu13": "Absent",
        "stu14": "Absent",
        "stu15": "Absent",
        "stu16": "Absent",
        "stu17": "Absent",
        "stu18": "Absent",
        "stu19": "Absent",
        "stu20": "Absent",
        "stu21": "Absent",
        "stu22": "Absent",
        "stu23": "Absent",
        "stu24": "Absent",
        "stu25": "Absent",
        "stu26": "Absent",
        "stu27": "Absent",
        "stu28": "Absent",
        "stu29": "Absent",
        "stu30": "Absent",
        "stu31": "Absent",
        "stu32": "Absent",
        "stu33": "Absent",
        "stu34": "Absent",
        "stu35": "Absent",
        "stu36": "Absent",
        "stu37": "Absent",
        "stu38": "Absent",
        "stu39": "Absent",
        "stu40": "Absent",
        "stu41": "Absent",
        "stu42": "Absent",
        "stu43": "Absent",
        "stu44": "Absent",
        "stu45": "Absent",
        "stu46": "Absent",
        "stu47": "Absent",
        "stu48": "Absent",
        "stu49": "Absent",
        "stu50": "Absent",
        "stu51": "Absent",
        "stu52": "Absent",
        "stu53": "Absent",
        "stu54": "Absent",
        "stu55": "Absent",
        "stu56": "Absent",
        "stu57": "Absent",
        "stu58": "Absent",
        "stu59": "Absent",
        "stu60": "Absent",
        "stu61": "Absent",
        "stu62": "Absent",
        "stu63": "Absent",
        "stu64": "Absent",
        "stu65": "Absent"
    },
    "Brindha": {
        "stu0": "Present",
        "stu1": "Present",
        "stu2": "Absent",
        "stu3": "Absent",
        "stu4": "Present",
        "stu5": "Present",
        "stu6": "Absent",
        "stu7": "Absent",
        "stu8": "Absent",
        "stu9": "Absent",
        "stu10": "Absent",
        "stu11": "Absent",
        "stu12": "Absent",
        "stu13": "Absent",
        "stu14": "Present",
        "stu15": "Absent",
        "stu16": "Present",
        "stu17": "Present",
        "stu18": "Present",
        "stu19": "Absent",
        "stu20": "Absent",
        "stu21": "Present",
        "stu22": "Present",
        "stu23": "Absent",
        "stu24": "Absent",
        "stu25": "Absent",
        "stu26": "Absent",
        "stu27": "Absent",
        "stu28": "Absent",
        "stu29": "Absent",
        "stu30": "Absent",
        "stu31": "Present",
        "stu32": "Present",
        "stu33": "Absent",
        "stu34": "Present",
        "stu35": "Absent",
        "stu36": "Absent",
        "stu37": "Absent",
        "stu38": "Present",
        "stu39": "Present",
        "stu40": "Absent",
        "stu41": "Present",
        "stu42": "Absent",
        "stu43": "Absent",
        "stu44": "Absent",
        "stu45": "Absent",
        "stu46": "Absent",
        "stu47": "Present",
        "stu48": "Absent",
        "stu49": "Present",
        "stu50": "Present",
        "stu51": "Absent",
        "stu52": "Present",
        "stu53": "Absent",
        "stu54": "Absent",
        "stu55": "Present",
        "stu56": "Absent",
        "stu57": "Present",
        "stu58": "Absent",
        "stu59": "Absent",
        "stu60": "Absent",
        "stu61": "Present",
        "stu62": "Absent",
        "stu63": "Present",
        "stu64": "Present",
        "stu65": "Present"
    },
    "DL": {
        "stu0": "Absent",
        "stu1": "Absent",
        "stu2": "Present",
        "stu3": "Present",
        "stu4": "Present",
        "stu5": "Present",
        "stu6": "Absent",
        "stu7": "Present",
        "stu8": "Present",
        "stu9": "Present",
        "stu10": "Present",
        "stu11": "Present",
        "stu12": "Present",
        "stu13": "Present",
        "stu14": "Absent",
        "stu15": "Present",
        "stu16": "Present",
        "stu17": "Absent",
        "stu18": "Present",
        "stu19": "Present",
        "stu20": "Absent",
        "stu21": "Absent",
        "stu22": "Absent",
        "stu23": "Present",
        "stu24": "Present",
        "stu25": "Present",
        "stu26": "Absent",
        "stu27": "Present",
        "stu28": "Present",
        "stu29": "Present",
        "stu30": "Present",
        "stu31": "Present",
        "stu32": "Absent",
        "stu33": "Present",
        "stu34": "Absent",
        "stu35": "Present",
        "stu36": "Present",
        "stu37": "Present",
        "stu38": "Present",
        "stu39": "Present",
        "stu40": "Present",
        "stu41": "Absent",
        "stu42": "Present",
        "stu43": "Absent",
        "stu44": "Present",
        "stu45": "Present",
        "stu46": "Present",
        "stu47": "Absent",
        "stu48": "Present",
        "stu49": "Absent",
        "stu50": "Absent",
        "stu51": "Present",
        "stu52": "Absent",
        "stu53": "Present",
        "stu54": "Present",
        "stu55": "Absent",
        "stu56": "Present",
        "stu57": "Absent",
        "stu58": "Present",
        "stu59": "Present",
        "stu60": "Present",
        "stu61": "Absent",
        "stu62": "Present",
        "stu63": "Absent",
        "stu64": "Absent",
        "stu65": "Absent"
    },
    "Test": {
        "stu0": "Absent",
        "stu1": "Absent",
        "stu2": "Absent",
        "stu3": "Absent",
        "stu4": "Present",
        "stu5": "Present",
        "stu6": "Absent",
        "stu7": "Absent",
        "stu8": "Absent",
        "stu9": "Absent",
        "stu10": "Absent",
        "stu11": "Absent",
        "stu12": "Absent",
        "stu13": "Absent",
        "stu14": "Absent",
        "stu15": "Absent",
        "stu16": "Absent",
        "stu17": "Absent",
        "stu18": "Absent",
        "stu19": "Absent",
        "stu20": "Absent",
        "stu21": "Absent",
        "stu22": "Absent",
        "stu23": "Absent",
        "stu24": "Absent",
        "stu25": "Absent",
        "stu26": "Absent",
        "stu27": "Absent",
        "stu28": "Absent",
        "stu29": "Absent",
        "stu30": "Absent",
        "stu31": "Absent",
        "stu32": "Absent",
        "stu33": "Absent",
        "stu34": "Absent",
        "stu35": "Absent",
        "stu36": "Absent",
        "stu37": "Absent",
        "stu38": "Absent",
        "stu39": "Absent",
        "stu40": "Absent",
        "stu41": "Absent",
        "stu42": "Absent",
        "stu43": "Absent",
        "stu44": "Absent",
        "stu45": "Absent",
        "stu46": "Absent",
        "stu47": "Absent",
        "stu48": "Absent",
        "stu49": "Absent",
        "stu50": "Absent",
        "stu51": "Absent",
        "stu52": "Absent",
        "stu53": "Absent",
        "stu54": "Absent",
        "stu55": "Absent",
        "stu56": "Absent",
        "stu57": "Absent",
        "stu58": "Absent",
        "stu59": "Absent",
        "stu60": "Absent",
        "stu61": "Absent",
        "stu62": "Absent",
        "stu63": "Absent",
        "stu64": "Absent",
        "stu65": "Absent"
    },
    "sample": {
        "stu0": "Present",
        "stu1": "Present",
        "stu2": "Present",
        "stu3": "Present",
        "stu4": "Present",
        "stu5": "Absent",
        "stu6": "Absent",
        "stu7": "Absent",
        "stu8": "Present",
        "stu9": "Present",
        "stu10": "Present",
        "stu11": "Present",
        "stu12": "Present",
        "stu13": "Present",
        "stu14": "Present",
        "stu15": "Present",
        "stu16": "Present",
        "stu17": "Present",
        "stu18": "Present",
        "stu19": "Present",
        "stu20": "Present",
        "stu21": "Absent",
        "stu22": "Present",
        "stu23": "Present",
        "stu24": "Absent",
        "stu25": "Absent",
        "stu26": "Present",
        "stu27": "Absent",
        "stu28": "Absent",
        "stu29": "Present",
        "stu30": "Present",
        "stu31": "Present",
        "stu32": "Present",
        "stu33": "Present",
        "stu34": "Present",
        "stu35": "Present",
        "stu36": "Present",
        "stu37": "Present",
        "stu38": "Present",
        "stu39": "Absent",
        "stu40": "Present",
        "stu41": "Present",
        "stu42": "Absent",
        "stu43": "Present",
        "stu44": "Present",
        "stu45": "Absent",
        "stu46": "Present",
        "stu47": "Present",
        "stu48": "Present",
        "stu49": "Present",
        "stu50": "Absent",
        "stu51": "Absent",
        "stu52": "Present",
        "stu53": "Present",
        "stu54": "Present",
        "stu55": "Present",
        "stu56": "Absent",
        "stu57": "Present",
        "stu58": "Present",
        "stu59": "Present",
        "stu60": "Absent",
        "stu61": "Present",
        "stu62": "Present",
        "stu63": "Present",
        "stu64": "Present",
        "stu65": "Present"
    },
    "90": {
        "stu0": "Present",
        "stu1": "Present",
        "stu2": "Present",
        "stu3": "Present",
        "stu4": "Present",
        "stu5": "Absent",
        "stu6": "Absent",
        "stu7": "Absent",
        "stu8": "Absent",
        "stu9": "Absent",
        "stu10": "Absent",
        "stu11": "Absent",
        "stu12": "Absent",
        "stu13": "Absent",
        "stu14": "Absent",
        "stu15": "Absent",
        "stu16": "Absent",
        "stu17": "Absent",
        "stu18": "Absent",
        "stu19": "Absent",
        "stu20": "Absent",
        "stu21": "Absent",
        "stu22": "Absent",
        "stu23": "Absent",
        "stu24": "Absent",
        "stu25": "Absent",
        "stu26": "Absent",
        "stu27": "Absent",
        "stu28": "Present",
        "stu29": "Absent",
        "stu30": "Absent",
        "stu31": "Absent",
        "stu32": "Absent",
        "stu33": "Absent",
        "stu34": "Absent",
        "stu35": "Absent",
        "stu36": "Absent",
        "stu37": "Absent",
        "stu38": "Absent",
        "stu39": "Absent",
        "stu40": "Absent",
        "stu41": "Absent",
        "stu42": "Absent",
        "stu43": "Absent",
        "stu44": "Absent",
        "stu45": "Absent",
        "stu46": "Absent",
        "stu47": "Absent",
        "stu48": "Absent",
        "stu49": "Absent",
        "stu50": "Absent",
        "stu51": "Absent",
        "stu52": "Absent",
        "stu53": "Absent",
        "stu54": "Absent",
        "stu55": "Absent",
        "stu56": "Absent",
        "stu57": "Absent",
        "stu58": "Absent",
        "stu59": "Absent",
        "stu60": "Absent",
        "stu61": "Absent",
        "stu62": "Present",
        "stu63": "Absent",
        "stu64": "Absent",
        "stu65": "Absent"
    }
}